<?xml version="1.0" encoding="utf-8"?>
<recette id="22763">
 <titre>Mes oeufs battus</titre>
 <type>Plat principal</type>
 <niveau>Très facile</niveau>
 <cout>Bon marché</cout>
 <ingredients>
 <p>4 œufs</p>
 <p>10 g de beurre</p>
 <p>sel et poivre du moulin</p>
 </ingredients>
 <preparation>
<![CDATA[
mettre le beurre dans une <recipient>poêle</recipient> de la dimension de 4 oeufs sur le <recipient>plat</recipient>. attendre que le blanc des oeufs commence à prendre. a ce moment là rabattre les oeufs les uns sur les autres en crevant les jaunes d’ oeufs. cela donne " une purée " d’ oeufs mousseux. saler et poivrer et <operation>servir aussitôt avec une bonne salade verte</operation> agrémentée si on le souhaite de lardons et de cerneaux de noix. attention cette recette est particulièrement rapide à effectuer, elle doit être faite à la dernière minute
]]>
 </preparation>
</recette>
