<?xml version="1.0" encoding="utf-8"?>
<recette id="10916">
 <titre>Gratin de poulet aux tagliatelles</titre>
 <type>Plat principal</type>
 <niveau>Moyennement difficile</niveau>
 <cout>Moyen</cout>
 <ingredients>
 <p>800 à 900 g d’ émincé de poulet</p>
 <p>300 g de tagliatelles vertes </p>
 <p>3 grosses gousses d’ ail</p>
 <p>200 g de fromage râpé (Gruyère) </p>
 <p>20 cl de gelée (poudre mélangée avec moitié vin blanc et moitié Madère) </p>
 <p>50 g de beurre </p>
 <p>sel, poivre </p>
 </ingredients>
 <preparation>
<![CDATA[
préchauffer le <recipient>four</recipient> à 180 ° c (thermostat 6). <operation>frottez fortement votre <recipient>plat</recipient> avec une gousse d’ <ingredient>ail</ingredient></operation>. répartissez le restant d’ <ingredient>ail</ingredient> finement coupé au fond du <recipient>plat</recipient>. <operation>mettez quelques coquilles de beurre</operation>. <operation>faites cuire les <ingredient>tagliatelles</ingredient> 7 à 8 min dans de l’ eau bouillante</operation> salée. <operation>faites dorer à la <recipient>poêle</recipient> votre émincé</operation>. <operation>egouttez les <ingredient>tagliatelles</ingredient></operation> <operation>disposez une couche de <ingredient>tagliatelles</ingredient> au fond du <recipient>plat</recipient></operation>. disposez votre <ingredient>émincé de poulet</ingredient>. <operation>recouvrez avec le reste de <ingredient>tagliatelles</ingredient></operation>. saler, poivrer, arroser avec votre <ingredient>gelée</ingredient>. parsemez généreusement de <ingredient>fromage</ingredient>. <operation>faire gratiner 30 min au <recipient>four</recipient> et servir très chaud</operation>.
]]>
 </preparation>
</recette>
