<?xml version="1.0" encoding="utf-8"?>
<recette id="165153">
 <titre>BOULETTE DE POULET AU CURRY</titre>
 <type>Plat principal</type>
 <niveau>Facile</niveau>
 <cout>Bon marché</cout>
 <ingredients>
 <p>2 filet de poulet assez gros</p>
 <p>1 oeuf</p>
 <p>1 morceau de pain</p>
 <p>2 verre de lait</p>
 <p>sel et poivre</p>
 <p>1 cuillère à café de curry</p>
 <p>50 g de gruyère râpé</p>
 <p>farine</p>
 </ingredients>
 <preparation>
<![CDATA[
la préparation est plus que facile: mettre dans le robot a mixer les 2 <ingredient>gros filet de poulet</ingredient>, l’ <ingredient>oeuf</ingredient>, le <ingredient>morceau de pain</ingredient> (environ 10/15 cm) préalablement trempé dans le <ingredient>lait</ingredient> et pressé afin qu il ne reste qu’ une pate, salé et poivré, ajouté un peu de gruyere rapé (facultatif) puis une bonne <ingredient>cuillère de curry</ingredient> (vous pouvez aussi ne pas mettre le <ingredient>curry</ingredient> et préparer une sauce au <ingredient>curry</ingredient> a part) mixer le tout. une fois mixé, <operation>formez des boulettes et passez dans la farine</operation> puis <operation>faites cuire à la poele avec un fond d’</operation> huile. c’ est un régal accompagnement possible: riz avec sauce au <ingredient>curry</ingredient>... accompagnement possible: riz avec sauce au <ingredient>curry</ingredient>...
]]>
 </preparation>
</recette>
