<?xml version="1.0" encoding="utf-8"?>
<recette id="227776">
 <titre>Poulet au cidre, bacon et champignons</titre>
 <type>Plat principal</type>
 <niveau>Facile</niveau>
 <cout>Bon marché</cout>
 <ingredients>
 <p>4 escalopes de poulet (ou dinde) </p>
 <p>500 g de champignons de Paris (ou plus selon les goûts) </p>
 <p>10 tranches de bacon</p>
 <p>50 cl de crème fraîche épaisse </p>
 <p>35 cl bouteille de cidre brut</p>
 <p>1 noisette de beurre</p>
 <p>1 pincée de sel</p>
 <p>1 pincée de poivre</p>
 <p>1 pincée de fond de veau</p>
 </ingredients>
 <preparation>
<![CDATA[
éplucher et émincer les <ingredient>champignons</ingredient>. couper le <ingredient>bacon</ingredient> en petits carrés de 1 cm. <operation>faire revenir sans matière grasse les <ingredient>champignons</ingredient> et le <ingredient>bacon</ingredient> avec un demi verre de <ingredient>cidre</ingredient></operation>. ajouter une grosse <ingredient>pincée de fond de veau</ingredient> et un peu d’ eau. <operation>laisser mijoter 10 min à feu doux pour que cela caramélise</operation>. retirer du feu. dans la même <recipient>poêle</recipient>, faire fondre une <ingredient>noisette de beurre</ingredient> et y <operation>faire cuire les <ingredient>escalopes</ingredient></operation>. ajouter petit à petit le reste du <ingredient>cidre</ingredient> et <operation>faire réduire</operation>. <operation>faire griller en fin de cuisson pour</operation> donner un meilleur goût à la sauce. rajouter le mélange <ingredient>bacon</ingredient> et <ingredient>champignons</ingredient> au <ingredient>cidre</ingredient> et <operation>laisser mijoter 5 minutes</operation>. ajouter la <ingredient>crème fraîche</ingredient> et la délayer pour <operation>obtenir un mélange épais et onctueux</operation>. saler et poivrer selon convenance. <operation>servir avec une purée maison avec des pomme de terre grossièrement</operation> écrasées. un saint nicolas de bourgueil rouge.
]]>
 </preparation>
</recette>
