<?xml version="1.0" encoding="utf-8"?>
<recette id="21553">
 <titre>Osso Bucco à la moutarde</titre>
 <type>Plat principal</type>
 <niveau>Facile</niveau>
 <cout>Moyen</cout>
 <ingredients>
 <p>6 rondelles de jarret de veau</p>
 <p>1 oignon</p>
 <p>1 gousse d’ ail</p>
 <p>2 cuillerées à soupe de moutarde</p>
 <p>1 cuillerée à soupe de concentré de tomate</p>
 <p>1 bouquet garni</p>
 <p>50 cl de bouillon de volaille</p>
 <p>1 à 2 cuillerées à soupe de farine</p>
 <p>1 cuillerée à soupe d’ huile d’ olive</p>
 <p>sel, poivre</p>
 </ingredients>
 <preparation>
<![CDATA[
farinez légèrement les tranches de <ingredient>jarret</ingredient> sur les deux faces. <operation>faites - les</operation> colorer de chaque côté dans une <recipient>poêle</recipient> avec l’ <ingredient>huile</ingredient> puis posez - les dans une <recipient>cocotte</recipient>. <operation>faites revenir l’ <ingredient>oignon</ingredient></operation> haché dans la <recipient>poêle</recipient>. <operation>ajoutez l’ <ingredient>ail</ingredient></operation> haché, la <ingredient>moutarde</ingredient> et le <ingredient>concentré de tomate</ingredient>. <operation>laissez cuire 30 secondes en</operation> remuant, <operation>délayez avec le <ingredient>bouillon</ingredient></operation>. <operation>versez dans la <recipient>cocotte</recipient></operation>. ajoutez <ingredient>bouquet garni</ingredient>, <ingredient>sel</ingredient> et <ingredient>poivre</ingredient>. <operation>laissez mijoter à couvert 1 h10</operation>. <operation>servez avec du riz</operation>.
]]>
 </preparation>
</recette>
