<?xml version="1.0" encoding="utf-8"?>
<recette id="23692">
 <titre>Tatin de courgettes au lard</titre>
 <type>Entrée</type>
 <niveau>Très facile</niveau>
 <cout>Bon marché</cout>
 <ingredients>
 <p>1 kg de courgettes</p>
 <p>15 tranches de lard</p>
 <p>2 gros oeufs</p>
 <p>100 g de dés de bacon ou de lardons fumés</p>
 <p>2 grosses cuillères à soupe de crème fraîche</p>
 <p>60 g de gruyère râpé</p>
 <p>sel, poivre, muscade, huile d’ olive</p>
 </ingredients>
 <preparation>
<![CDATA[
chemisez un <recipient>moule</recipient> à cake de <ingredient>tranches de lard</ingredient> (fond et bords). epluchez les <ingredient>courgettes</ingredient>. <operation>coupez - les en rondelles fines</operation>. <operation>faites les</operation> <operation>revenir dans une <recipient>poêle</recipient> avec de l’ <ingredient>huile</ingredient> d’ <ingredient>olive</ingredient> jusqu’ à ce qu’ elles soient</operation> fondantes. dans un saladier, <operation>mélangez les <ingredient>oeufs</ingredient>, la <ingredient>crème</ingredient>, le gruyère, le <ingredient>bacon</ingredient></operation>. <operation>assaisonnez</operation>. <operation>ajoutez les</operation> <ingredient>courgettes</ingredient> et <operation>mélangez bien</operation>. <operation>remplir le <recipient>moule</recipient> avec la préparation</operation> et <operation>faites cuire environ 40</operation> mn à thermostat 6 (180 ° c). démoulez et <operation>servez tiède</operation>. cette entrée est simple, très jolie et légère!
]]>
 </preparation>
</recette>
