<?xml version="1.0" encoding="utf-8"?>
<recette id="29894">
 <titre>Bonet (dessert italien au cacao) </titre>
 <type>Dessert</type>
 <niveau>Moyennement difficile</niveau>
 <cout>Moyen</cout>
 <ingredients>
 <p>4 oeufs</p>
 <p>50 g de cassonade (+ 50 g si on fait un caramel) </p>
 <p>25 cl de lait</p>
 <p>3 cuillères à soupe de cacao non sucré</p>
 <p>50 de biscuits amaretti secs</p>
 <p>1 cuillère à soupe de rhum</p>
 <p>1 cuillère à soupe d’ amaretto (ou de marsala) </p>
 </ingredients>
 <preparation>
<![CDATA[
attention: on peut sauter l’ étape’ caramel’ (en particulier, si on fait la recette dans des moules en silicone), qui est à mon avis la plus technique. préchauffer le <recipient>four</recipient> à 140 ° c environ. enfourner un <recipient>moule</recipient> à savarin de 1 l, ou 8 petits ramequins individuels. <operation>faire chauffer 50 g de <ingredient>cassonade</ingredient> dans une <recipient>casserole</recipient>, en</operation> remuant, jusqu’ à ce qu’ elle forme un caramel lisse et brun. verser alors le caramel dans le (s) <recipient>moule</recipient> (s) chaud, en les inclinant pour bien enrober l’ intérieur. ecraser les <ingredient>biscuits amaretti</ingredient> (par exemple dans un mixer, ou en les mettant dans un sac en plastique et en utilisant un rouleau à pâtisserie ou autre objet lourd). porter de l’ eau à ébullition pour un <recipient>bain - marie</recipient>. dans un saladier, fouetter vigoureusemet les <ingredient>oeufs</ingredient>. rajouter 50 g de <ingredient>cassonade</ingredient> et bien battre jusqu’ à ce qu’ elle soit dissoute. ajouter ensuite le <ingredient>cacao</ingredient>, le lait, le <ingredient>rhum</ingredient> et l’ <ingredient>amaretto</ingredient>. enfin, rajouter les <ingredient>amaretti</ingredient> émiettés. poser le (s) <recipient>moule</recipient> (s) dans un grand <recipient>plat</recipient> à <recipient>four</recipient>, sur la grille du <recipient>four</recipient>. <operation>remplir avec la préparation,</operation> et <operation>recouvrir de papier aluminium</operation>. <operation>remplir ensuite le récipient d’ eau bouillante,</operation> et <operation>faire cuire environ 20 minutes au <recipient>bain - marie</recipient></operation>. après cuisson, <operation>sortir du <recipient>bain - marie</recipient></operation>, <operation>laisser refroidir,</operation> et mettre ensuite au <recipient>réfrigérateur</recipient>. déguster frais, avec par exemple de la crème anglaise ou de la crème chantilly. accompagner d’ <ingredient>amaretti</ingredient> moelleux. la recette’ classique’ est avec du caramel, mais c’ est bon même sans (et plus simple). dans ce cas, il pourra être utile de beurrer ou huiler légèrement le <recipient>moule</recipient> (surtout s’ il n’ est pas anti-adhésif) si l’ on veut démouler le dessert. on peut aussi le servir avec un peu de miel. le temps de cuisson peut être assez variable selon le <recipient>four</recipient>, le <recipient>moule</recipient>, etc. (vérifier éventuellement la cuisson avec une pique qui doit <operation>ressortir</operation> <ingredient>sèche</ingredient>). dessert à préparer la veille de préférence.
]]>
 </preparation>
</recette>
