<?xml version="1.0" encoding="utf-8"?>
<recette id="26578">
 <titre>Chou farci en cocotte</titre>
 <type>Plat principal</type>
 <niveau>Facile</niveau>
 <cout>Moyen</cout>
 <ingredients>
 <p>1 gros chou</p>
 <p>500 g de chair à saucisse</p>
 <p>quelques bardes de lard</p>
 <p>quelques couennes</p>
 <p>2 carottes</p>
 <p>1 oignon</p>
 <p>25 cl de bouillon </p>
 <p>1 verre de vin blanc</p>
 <p>sel, poivre </p>
 </ingredients>
 <preparation>
<![CDATA[
nettoyer et parer le <ingredient>chou</ingredient>, puis le <operation>faire blanchir 10 min dans l’ eau bouillante</operation> salée. pendant ce temps, peler et détailler les <ingredient>carottes</ingredient> et les <ingredient>oignons</ingredient> en rondelles. tapisser une grande <recipient>cocotte</recipient> de <ingredient>couennes</ingredient> de <ingredient>lard</ingredient>. egoutter ensuite le <ingredient>chou</ingredient>, puis le presser pour extraire toute l’ eau absorbée. le farcir avec un peu de <ingredient>chair à saucisse</ingredient> au centre, puis <operation>répartir la farce entre ses feuilles en</operation> veillant à ne pas les casser. envelopper le <ingredient>chou</ingredient> farci de <ingredient>bardes de lard</ingredient> puis le ficeler avec de la ficelle de cuisine. déposer ensuite le <ingredient>chou</ingredient> farci sur le lit de <ingredient>couennes</ingredient> et l’ entourer de rondelles d’ <ingredient>oignons</ingredient> et de <ingredient>carottes</ingredient>. saler, poivrer, puis arroser le <ingredient>chou</ingredient> de <ingredient>vin</ingredient> et de <ingredient>bouillon</ingredient>. <operation>laisser cuire 3 h à couvert à feu doux en le mouillant de temps en temps</operation>. <operation>sortir le <ingredient>chou</ingredient> de la <recipient>cocotte</recipient>, le déficeler et lui</operation> ôter les <ingredient>bardes</ingredient> qui l’ entourent. découper le <ingredient>chou</ingredient> en quartiers puis le dresser sur un <recipient>plat</recipient> de service chaud. le napper de jus de cuisson et servir. pour éviter que le <ingredient>chou</ingredient> ne se défasse à la cuisson, vous pouvez l’ envelopper dans une mousseline pour qu’ il garde sa forme d’ origine.
]]>
 </preparation>
</recette>
