<?xml version="1.0" encoding="utf-8"?>
<recette id="34065">
 <titre>Crumble pommes cannelle à la vergeoise</titre>
 <type>Dessert</type>
 <niveau>Très facile</niveau>
 <cout>Bon marché</cout>
 <ingredients>
 <p>800 g de pommes acidulées</p>
 <p>160 g de vergoise blonde vanille</p>
 <p>cannelle en poudre</p>
 <p>110 g de margarine</p>
 <p>150 g de farine</p>
 <p>100 g de raisins secs blonds</p>
 <p>et/ou 1 grosse poignée de baies rouges surgelées (groseilles, cassis, framboises, myrtilles...) </p>
 </ingredients>
 <preparation>
<![CDATA[
<operation>faire gonfler les <ingredient>raisins</ingredient> à l’ eau</operation> tiède. allumer le <recipient>four</recipient> (150 ° c). beurrer un <recipient>plat</recipient> allant au <recipient>four</recipient> (10 g). <operation>garnir avec les <ingredient>pommes</ingredient> (pelées</operation> et coupées en minces quartiers), les <ingredient>raisins</ingredient> égouttés et / ou les fruits <ingredient>rouges</ingredient> encore <ingredient>surgelées</ingredient>. saupoudrer avec 80 g de vergeoise et la <ingredient>cannelle</ingredient>. mettre 15 mn au <recipient>four</recipient> à 150 ° c. pendant ce temps, préparer la pâte: travailler à la main les 100 g de beurre restant, la farine, et les 80 g de vergeoise restante jusqu’ à obtention d’ une pâte grossièrement sablée. la <operation>répartir sur les <ingredient>pommes</ingredient> fondues</operation>. remettre au <recipient>four</recipient> 30 mn jusqu’ à coloration de la pâte. servir tiède, avec un coulis de fruit <ingredient>rouge</ingredient> et éventuellement une boule de glace à la <ingredient>vanille</ingredient>. les temps de cuisson peuvent varier d’ un <recipient>four</recipient> à l’ autre: le mien chauffe assez fort et je compte 10 + 20 minutes de cuisson.
]]>
 </preparation>
</recette>
