<?xml version="1.0" encoding="utf-8"?>
<recette id="26956">
 <titre>Cake hivernal</titre>
 <type>Plat principal</type>
 <niveau>Facile</niveau>
 <cout>Bon marché</cout>
 <ingredients>
 <p>100 g de farine de châtaigne</p>
 <p>80 g de Maïzena</p>
 <p>1 sachet de levure</p>
 <p>3 oeufs</p>
 <p>10 cl de lait</p>
 <p>5 cl de d’ huile d’ olive</p>
 <p>4 tranches fine de jambon cru</p>
 <p>8 figues séchées</p>
 <p>1/2 bûche de fromage de chèvre</p>
 <p>sel, poivre</p>
 </ingredients>
 <preparation>
<![CDATA[
préchauffer le <recipient>four</recipient> à 200 ° c. dans une <recipient>terrine</recipient>, mélanger la farine de <ingredient>châtaigne</ingredient>, la <ingredient>maïzena</ingredient> et la <ingredient>levure</ingredient>. dans un bol, battre les <ingredient>oeufs</ingredient>. ajouter le lait et l’ huile. saler et poivrer. mélanger la préparation à l’ <ingredient>oeuf</ingredient> avec le mélange sec. ajouter enfin le <ingredient>jambon</ingredient>, les <ingredient>figues</ingredient> et le <ingredient>fromage</ingredient> découpés en gros morceaux. mélanger délicatement. <operation>versez la préparation dans un <recipient>moule</recipient> à cake beuré et fariné</operation>. enfourner 40 mn. vérifier la cuisson au couteau. servir tiède avec une salade verte. bon appétit. <operation>veillez à bien</operation> tamiser la farine de <ingredient>châtaigne</ingredient> pour éviter les grumeaux.
]]>
 </preparation>
</recette>
