<?xml version="1.0" encoding="utf-8"?>
<recette id="47124">
 <titre>Nid de Pâques au pralin</titre>
 <type>Dessert</type>
 <niveau>Moyennement difficile</niveau>
 <cout>Moyen</cout>
 <ingredients>
 <p>Pour le biscuit: </p>
 <p>1 yaourt nature</p>
 <p>3 œufs</p>
 <p>sucre</p>
 <p>farine</p>
 <p>1 sachet de levure chimique</p>
 <p>huile</p>
 <p>2 cuillères à soupe d’ eau de rose (facultatif) Pour la crème: </p>
 <p>1 bouteille de crème fraîche </p>
 <p>150 g de pralin </p>
 <p>50 g de sucre </p>
 <p>1 sachet de fixe chantilly</p>
 <p>Pour la décoration: </p>
 <p>75 g de chocolat noir + un peu de lait</p>
 <p>1 petite poule en chocolat</p>
 <p>petits œufs de couleurs en sucre</p>
 <p>vermicelles en chocolat + pralin</p>
 </ingredients>
 <preparation>
<![CDATA[
le <ingredient>biscuit</ingredient>: dans une jatte, <operation>versez le pot de</operation> <ingredient>yaourt</ingredient> puis <operation>rincez - le pot</operation> et <operation>servez vous en comme doseur pour les autres ingrédients</operation>. <operation>ajoutez les 3 <ingredient>œufs</ingredient>, ainsi que 2 pots de <ingredient>sucre</ingredient></operation>. battez le tout au batteur, jusqu’ à ce que le mélange devienne mousseux. ensuite, rajoutez 3 pots de farine et le <ingredient>sachet de levure</ingredient>. <operation>mélangez doucement</operation>, incorporez 1 pot d’ huile et les 2 <ingredient>cuillères à soupe</ingredient> d’ <ingredient>eau de rose</ingredient>. <operation>beurrez un <recipient>moule</recipient> rond</operation> et <operation>versez le mélange</operation> dedans. enfournez à <recipient>four</recipient> chaud (150 ° c / th 5), pendant environ 40 min. pour <ingredient>la crème</ingredient>: versez la <ingredient>crème fraîche</ingredient> dans une jatte, puis battez énergiquement jusqu’ à ce que la <ingredient>crème</ingredient> monte en <ingredient>chantilly</ingredient>. lorsque la <ingredient>crème</ingredient> commence à monter, <operation>incorporez le mélange cremfix et le <ingredient>sucre</ingredient></operation>. <operation>battez encore jusqu’ à ce que la contenance de la <ingredient>chantilly</ingredient></operation> soit ferme. ensuite, <operation>ajoutez le <ingredient>pralin</ingredient> à l’</operation> aide d’ une spatule jusqu’ à ce que le mélange soit homogène, et <operation>réservez au frais</operation>. montage du gâteau: lorsque votre gâteau est complètement refroidi, <operation>coupez - le en 2, dans le sens de la largeur, afin d’</operation> <operation>obtenir 2 disques</operation>. la partie du bas doit être plus épaisse que celle du haut! <operation>prenez la partie du haut</operation> et <operation>coupez un rond au milieu du disque</operation> (utilisez un bol pour vous aider à suivre la forme d’ un rond, le diamètre ne doit pas être trop grand!). enduisez la partie du bas de crème avec les 3/4 de <ingredient>la crème</ingredient>, <operation>disposez ensuite le disque du haut par dessus</operation>. si vous <operation>avez tout suivi, vous</operation> devez avoir un trou dans votre gâteau! pour la déco, <operation>faites fondre la <ingredient>chocolat</ingredient> avec le <ingredient>lait</ingredient> pour</operation> <operation>faire un glaçage (vous</operation> pouvez ajoutez aussi un peu d’ <ingredient>eau de rose</ingredient>). <operation>etalez le <ingredient>chocolat</ingredient> sur le dessus du gâteau, sans en</operation> mettre dans le trou où se trouve la <ingredient>crème</ingredient>. puis, avec le reste de <ingredient>crème</ingredient>, <operation>enduisez le contour du gâteau</operation>. disposez la <ingredient>poule en chocolat</ingredient> dans le trou (le nid), avec les <ingredient>petits œufs en sucre</ingredient> autour. décorez le <ingredient>chocolat</ingredient> de <ingredient>pralin</ingredient> et de <ingredient>vermicelles en chocolat</ingredient>, et placez au frais avant de <operation>servir</operation>.
]]>
 </preparation>
</recette>
