<?xml version="1.0" encoding="utf-8"?>
<recette id="27515">
 <titre>Tom Ka (Soupe de lait coco) </titre>
 <type>Entrée</type>
 <niveau>Très facile</niveau>
 <cout>Moyen</cout>
 <ingredients>
 <p>1/4 l de bouillon de volaille</p>
 <p>2 boîtes de 400 ml de lait coco (environ, à adapter en fonction des contenances des boîtes que vous trouvez) </p>
 <p>400 g de poulet</p>
 <p>du gingembre (une racine d’ environ 2 à 3 cm, selon le goût) </p>
 <p>quelques branches de citronnelle</p>
 <p>Pour les égumes de votre choix, en fonction de vos placards, pour un volume équivalent à un gros bol: </p>
 <p>feuilles de chou chinois coupées en morceaux de 2 cm environ</p>
 <p>champignons noirs</p>
 <p>céleri coupé en très fines branches</p>
 <p>quelques rondelles de poireau</p>
 <p>poivron coupé en lanières</p>
 <p>le jus d’ un citron vert</p>
 <p>6 piments rouges (que vous pouvez remplacer par une cuillère à café de purée de piments) Attention, réduire les doses si vous n’ aimez pas épicé</p>
 <p>4 cuillères à soupe de sauce nuoc mam</p>
 <p>1 cuillère à soupe de sauce soja</p>
 <p>1 cuillère à café de sucre</p>
 </ingredients>
 <preparation>
<![CDATA[
couper le <ingredient quantite=1>gingembre</ingredient> en <ingredient quantite=1>très</ingredient> petits <ingredient quantite=1>morceaux</ingredient>, ou le hacher. dans une <recipient>cocotte</recipient> ou une grande <recipient>casserole</recipient>, <operation temps=6.86min espace=19>faire chauffer à feu moyen le <ingredient quantite=1>gingembre</ingredient> dans le <ingredient quantite=1>bouillon</ingredient> (que vous</operation> pouvez préparer avec un cube de <ingredient quantite=1>bouillon</ingredient>). bien <operation temps=6.86min espace=19>couvrir et ne pas</operation> laisser bouillir à <ingredient quantite=1>gros bouillons</ingredient> pour éviter l’ évaporation. pendant ce temps, préparer tous les légumes, arrosez avec le <ingredient quantite=1>jus</ingredient> de <ingredient quantite=1>citron</ingredient>, la <ingredient quantite=4>sauce nuoc mam</ingredient>, la <ingredient quantite=4>sauce soja</ingredient> et saupoudrer avec le <ingredient quantite=1>sucre</ingredient>. <ingredient quantite=1>couper</ingredient> le <ingredient quantite=1>poulet</ingredient> en petits <ingredient quantite=1>morceaux</ingredient> (de 1 <ingredient quantite=1>cm</ingredient> x 2 <ingredient quantite=1>cm</ingredient> environ). verser le lait <ingredient quantite=1>coco</ingredient> dans le <ingredient quantite=1>bouillon</ingredient>. ajouter les légumes et la viande. porter à ébullition en conservant de petits <ingredient quantite=1>bouillons</ingredient>. <operation temps=0.25min espace=19>couvrir</operation> et <operation temps=6.86min espace=19>laisser cuire à feu moyen jusqu’ à ce que la viande soit</operation> cuite (environ 10 min pour des <ingredient quantite=1>morceaux</ingredient> de la taille indiquée). en <ingredient quantite=1>fin</ingredient> de cuisson, ajouter les <ingredient quantite=6>piments</ingredient> ou la purée de <ingredient quantite=6>piments</ingredient> préalablement délayée dans un <ingredient quantite=1>bol</ingredient> avec un peu de la <ingredient quantite=4>soupe</ingredient> (pour faciliter le mélange). servir <ingredient quantite=1>très</ingredient> chaud. vous pouvez le servir avec du riz pour un <recipient>plat</recipient> principal. vous pouvez également préparer cette recette avec du porc ou des crevettes décortiquées.
]]>
 </preparation>
</recette>
