<?xml version="1.0" encoding="utf-8"?>
<recette id="11764">
 <titre>Galettes de pommes de terre alsaciennes</titre>
 <type>Plat principal</type>
 <niveau>Moyennement difficile</niveau>
 <cout>Moyen</cout>
 <ingredients>
 <p>800 g de pommes de terre</p>
 <p>1 oignon</p>
 <p>2 oeufs</p>
 <p>10 cl d’ huile</p>
 <p>persil</p>
 <p>sel, poivre</p>
 <p>muscade</p>
 </ingredients>
 <preparation>
<![CDATA[
laver, éplucher et râper les <ingredient quantite=1>pommes de terre</ingredient> sur une râpe pas trop fine. <operation temps=6.86min espace=10>laisser égoutter dans une <recipient>passoire</recipient></operation>. verser dans une <recipient>terrine</recipient> et et ajouter <ingredient quantite=2>oeufs</ingredient>, <ingredient quantite=1>oignon</ingredient> haché, <ingredient quantite=1>persil</ingredient> haché, <ingredient quantite=1>sel</ingredient>... malaxer et <operation temps=6.86min espace=10>faire frire les galettes dans une <recipient>poêle</recipient></operation>.
]]>
 </preparation>
</recette>
