<?xml version="1.0" encoding="utf-8"?>
<recette id="21992">
 <titre>Courgettes au quinoa</titre>
 <type>Plat principal</type>
 <niveau>Facile</niveau>
 <cout>Bon marché</cout>
 <ingredients>
 <p>4 courgettes</p>
 <p>2 verres de quinoa</p>
 <p>400 g de viande de boeuf haché</p>
 <p>1 gros oignon</p>
 <p>3 carottes</p>
 <p>persil</p>
 <p>huile d’ olive</p>
 <p>sel, poivre</p>
 </ingredients>
 <preparation>
<![CDATA[
couper les extrémités des <ingredient quantite=4>courgettes</ingredient>, les couper en deux dans le sens de la longueur, puis les cuire 5 mn à l’ eau bouillante salée. les égoutter. ajouter dans une <recipient>casserole</recipient> 4 <ingredient quantite=2>verres</ingredient> d’ eau froide et 2 <ingredient quantite=2>verres de quinoa</ingredient> que vous aurez préalablement lavé. porter le tout à ébullition et <operation temps=15.0min espace=12>laisser sur le feu 15 mn</operation>. râper les <ingredient quantite=3>carottes</ingredient>, <operation temps=6.86min espace=12>coupez l’ <ingredient quantite=1>oignon</ingredient></operation>. faire revenir le <ingredient quantite=1>boeuf haché</ingredient>, les <ingredient quantite=3>carottes</ingredient> et l’ <ingredient quantite=1>oignon</ingredient> dans une <recipient>poêle</recipient> avec un peu d’ huile d’ <ingredient quantite=1>olive</ingredient>. saler, poivrer. ajouter le <ingredient quantite=1>persil</ingredient>. creuser les <ingredient quantite=4>courgettes</ingredient> avec une cuillère et les <operation temps=6.86min espace=12>garnir avec la farce</operation>. dans un <recipient>plat</recipient>, disposer les <ingredient quantite=4>courgettes</ingredient> et cuire 20 mn au <recipient>four</recipient>, thermostat 6/7 (200 ° c). vin rouge léger et frais
]]>
 </preparation>
</recette>
