<?xml version="1.0" encoding="utf-8"?>
<recette id="91903">
 <titre>Tarte au thon et à la purée de tomate</titre>
 <type>Entrée</type>
 <niveau>Très facile</niveau>
 <cout>Bon marché</cout>
 <ingredients>
 <p>1 pâte feuilletée- 400 gr de thon au naturel- 250 gr de purée de tomates- 3 oeufs- 1 oignon- 1 cuillère à soupe de chapelure- sel, poivre. </p>
 </ingredients>
 <preparation>
<![CDATA[
<operation temps=6.86min espace=4>étalez la pâte dans un <recipient><recipient>moule</recipient> à tarte</recipient></operation>. <operation temps=6.86min espace=4>piquez le fond avec une fourchette</operation> puis <operation temps=6.86min espace=4>saupoudrez de chapelure le fond de la pâte (pour la chapelure, j’</operation> écrase deux biscottes). puis <operation temps=6.86min espace=4>mélangez dans un <recipient>saladier</recipient>, le <ingredient quantite=1>thon</ingredient>, la purée de tomates, les oeufs et l’ oignon</operation> coupé en petits morceaux ou haché. <operation temps=0.25min espace=4>salez</operation> et <operation temps=0.5min espace=4>poivrez</operation>. puis <operation temps=6.86min espace=4>versez la préparation sur la tarte</operation> et mettre à <recipient>four</recipient> chaud pendant 45 minutes. les enfants se régalent quand je <operation temps=6.86min espace=4>fais cette tarte</operation>.
]]>
 </preparation>
</recette>
