<?xml version="1.0" encoding="utf-8"?>
<recette id="16872">
 <titre>Chichis-frégi</titre>
 <type>Dessert</type>
 <niveau>Facile</niveau>
 <cout>Bon marché</cout>
 <ingredients>
 <p>500 g de farine</p>
 <p>10 g de levure de boulanger</p>
 <p>1 cuillère à soupe de fleur d’ oranger</p>
 <p>une pincée de sel</p>
 <p>sucre en poudre + un sachet de sucre vanillé (pour l’ enrobage) </p>
 <p>eau tiède</p>
 <p>un bain de friture</p>
 </ingredients>
 <preparation>
<![CDATA[
<operation temps=6.86min espace=9>mettez la farine dans un <recipient>cul de poule</recipient></operation> et <operation temps=6.86min espace=9>faites - y une fontaine</operation>. ajoutez dans la fontaine la <ingredient quantite=1>pincée de sel</ingredient> et la <ingredient quantite=1>fleur</ingredient> d’ <ingredient quantite=1>oranger</ingredient>. délayez la <ingredient quantite=1>levure</ingredient> dans un verre d’ <ingredient quantite=1>eau tiède</ingredient> et <operation temps=6.86min espace=9>ajoutez - la à la farine</operation>. mélanger le tout afin d’ <operation temps=6.86min espace=9>obtenir une pâte molle</operation> et souple qui se détache de la main (ajoutez un peu d’ <ingredient quantite=1>eau tiède</ingredient> si besoin). <operation temps=6.86min espace=9>couvrez le <recipient>cul de poule</recipient> avec un torchon</operation> et <operation temps=6.86min espace=9>laissez la pâte</operation> reposer pendant environ 2 heures dans un endroit <ingredient quantite=1>tiède</ingredient>, afin qu’ elle double de volume. <operation temps=10.0min espace=9>faites chauffer l’</operation> huile de <ingredient quantite=1>friture</ingredient>, <operation temps=6.86min espace=9>remplissez une poche à patisserie avec la pâte</operation>. <operation temps=6.86min espace=9>pressez la poche en</operation> partant du centre de la bassine et <operation temps=6.86min espace=9>faites couler la pâte en cercles dans la bassine (si vous n’ avez pas de poche</operation>, <operation temps=6.86min espace=9>faites des petits boudins en</operation> <operation temps=6.86min espace=9>faisant rouler la pâte entre vos mains</operation>). lorsque le boudin est bien doré, <operation temps=6.86min espace=9>retirez - le,</operation> et roulez - le dans le mélange <ingredient quantite=1>sucre + sucre</ingredient> vanillé. <operation temps=6.86min espace=9>servez <ingredient quantite=1>tiède</ingredient></operation>. important: attention à ne pas trop monter l’ huile en température! si vous <operation temps=6.86min espace=9>dépassez les 200 ° c, les chichis que vous</operation> plongez dans le <ingredient quantite=1>bain de friture</ingredient> peuvent " exploser " et vous blesser. de manière générale, <operation temps=6.86min espace=9>faites attention avec la</operation> <ingredient quantite=1>friture</ingredient>: plonger des ingrédients froids dans un <ingredient quantite=1>bain</ingredient> d’ huile bouillante crée un choc thermique. <operation temps=6.86min espace=9>protégez -vous les mains</operation> et <operation temps=6.86min espace=9>faites attention aux projections</operation>.
]]>
 </preparation>
</recette>
