<?xml version="1.0" encoding="utf-8"?>
<recette id="31010">
 <titre>Crêpes vietnamiennes au chou</titre>
 <type>Plat principal</type>
 <niveau>Très facile</niveau>
 <cout>Bon marché</cout>
 <ingredients>
 <p>1 chou blanc 500 g</p>
 <p>1 cuillère à soupe de semoule couscous fin</p>
 <p>1 oignon</p>
 <p>300 g de farine</p>
 <p>2 cuillères à soupe de poudre de curry</p>
 <p>300 g de poitrine de porc</p>
 <p>1 cuillère à soupe d’ huile de sésame</p>
 <p>1 cuillère à soupe d’ huile végétale</p>
 <p>2 à 3 branches de menthe fraîche</p>
 <p>2 à 3 branches de coriandre fraîche</p>
 <p>nuoc man</p>
 <p>quelques feuilles de salade</p>
 </ingredients>
 <preparation>
<![CDATA[
pour la pâte à crêpe: mélanger la farine avec le <ingredient quantite=2>curry</ingredient>, la <ingredient quantite=1>semoule de couscous</ingredient>, avec de l’ eau pour que la pâte soit bien homogène mais pas trop liquide quand même. <operation temps=6.86min espace=15>laisser reposer pendant le temps de</operation> préparer le reste. faire cuire la <ingredient quantite=1>poitrine de porc</ingredient> dans de l’ eau salée 3/4 d’ heure ; une fois cuite l’ émincer et <operation temps=6.86min espace=15>laisser de côté</operation>. le <ingredient quantite=1>chou</ingredient> et les <ingredient quantite=1>oignons</ingredient>: les émincer et faire cuire le tout dans une <recipient>poêle</recipient> avec l’ <ingredient quantite=1>huile de sésame</ingredient> et l’ huile <ingredient quantite=1>végétale</ingredient>. dans une grande <recipient>poêle</recipient>: mettre la pâte à crêpe, étaler bien la pâte dans toute la <recipient>poêle</recipient>. y ajouter dessus: un peu de <ingredient quantite=1>chou</ingredient> préalablement cuit (2 <ingredient quantite=1>cuillères à soupe</ingredient> à peu près), ainsi que des lamelles de <ingredient quantite=1>poitrine de porc</ingredient> cuite (3 à 4 lamelles). une fois la pâte cuite, fermer la crêpe en rabattant un côté par dessus le <ingredient quantite=1>chou</ingredient> et la viande et mettre celle-ci dans une assiette. pour manger: prendre une <ingredient quantite=1>feuille de salade</ingredient>, y mettre un peu de crêpe farcie, de la <ingredient quantite=2>menthe</ingredient>, de la <ingredient quantite=2>coriandre</ingredient>, et tremper dans le <ingredient quantite=1>nuoc man</ingredient>. bon appétit. rouge
]]>
 </preparation>
</recette>
