<?xml version="1.0" encoding="utf-8"?>
<recette id="83983">
 <titre>Steaks hachés au roquefort</titre>
 <type>Plat principal</type>
 <niveau>Très facile</niveau>
 <cout>Bon marché</cout>
 <ingredients>
 <p>500g de viande hachée</p>
 <p>150 g de roquefort</p>
 <p>huile d’ olive, beurre</p>
 <p>sel et poivre</p>
 <p>paprika</p>
 <p>1 cuillère de crème fraiche</p>
 </ingredients>
 <preparation>
<![CDATA[
dans un <recipient>plat</recipient> de préparation, mélanger la <ingredient quantite=1>viande</ingredient> avec du <ingredient quantite=1>paprika</ingredient>, selon votre goût, de l’ huile d’ <ingredient quantite=1>olive</ingredient>, du <ingredient quantite=1>sel</ingredient> et du poivre. préparer 4 boules et les <operation temps=6.86min espace=9>aplatir pour</operation> <operation temps=6.86min espace=9>obtenir la forme d’ un steak</operation> haché. mettre au frais. dans un mixer, mettre le <ingredient quantite=1>roquefort</ingredient> et la <ingredient quantite=1>crème fraiche</ingredient>. mixer pour <operation temps=6.86min espace=9>obtenir une pâte lisse mais ferme</operation>. épaissir au besoin avec de la maïzena. <operation temps=6.86min espace=9>ouvrir en deux les steaks</operation> et déposer une dose de <ingredient quantite=1>crème</ingredient> de <ingredient quantite=1>roquefort</ingredient>. refermer avec l’ autre partie du steak et bien écraser les bords pour garder le fromage à l’ intérieur. dans une <recipient>poêle</recipient>, <operation temps=6.86min espace=9>faites chauffer le beurre</operation>. une fois doré, ajouter une <ingredient quantite=1>cuillère</ingredient> à café d’ huile d’ <ingredient quantite=1>olive</ingredient>. déposer les steaks et <operation temps=6.86min espace=9>faire cuire selon le goût</operation>. déguster avec une salade verte aux croutons a l’ ailavec des frites de carottes, c’ est un <recipient>plat</recipient> assez équilibré.
]]>
 </preparation>
</recette>
