<?xml version="1.0" encoding="utf-8"?>
<recette id="72398">
 <titre>Saumon et poireaux fondants</titre>
 <type>Plat principal</type>
 <niveau>Très facile</niveau>
 <cout>Moyen</cout>
 <ingredients>
 <p>500 g de filet de saumon</p>
 <p>600 g de poireaux en rondelles</p>
 <p>aneth</p>
 <p>jus de citron jaune (environ 1 demi-bouteille toute prête) </p>
 <p>huile d’ olive</p>
 </ingredients>
 <preparation>
<![CDATA[
dans un <recipient>plat</recipient>, mettre le <ingredient quantite=1>saumon</ingredient> (au centre du <recipient>plat</recipient>) et ajouter tout autour les <ingredient quantite=1>poireaux en rondelles</ingredient>. arroser le <ingredient quantite=1>saumon</ingredient> et les <ingredient quantite=1>poireaux</ingredient> d’ huile d’ <ingredient quantite=1>olive</ingredient> puis de <ingredient quantite=1>citron</ingredient>. saupoudrer le <ingredient quantite=1>saumon</ingredient> d"aneth. mettre au <recipient>four</recipient> à 220 °, thermostat 7. toutes les 10 min environ, arroser le <ingredient quantite=1>saumon</ingredient> avec le <ingredient quantite=1>jus</ingredient> et remuer les <ingredient quantite=1>poireaux</ingredient>. <operation temps=40.0min espace=8>laisser cuire 30 à 40 min selon l’ épaisseur du <ingredient quantite=1>saumon</ingredient> ou s’ il est</operation> congelé. vous pouvez accompagner le <ingredient quantite=1>saumon</ingredient> et les <ingredient quantite=1>poireaux</ingredient> avec du riz thaï et de la crème fraiche épaisse.
]]>
 </preparation>
</recette>
