<?xml version="1.0" encoding="utf-8"?>
<recette id="45534">
 <titre>Tarte crumble banane rhubarbe et spéculoos</titre>
 <type>Dessert</type>
 <niveau>Très facile</niveau>
 <cout>Bon marché</cout>
 <ingredients>
 <p>90 g de speculoos</p>
 <p>90 g de beurre</p>
 <p>90 g de sucre roux</p>
 <p>3 ou 4 bananes selon la taille</p>
 <p>compote de rhubarbe</p>
 <p>1 pâte feuilletée</p>
 </ingredients>
 <preparation>
<![CDATA[
etaler la <ingredient quantite=1>pâte</ingredient> dans le <recipient>plat</recipient> et y verser la <ingredient quantite=1>compote de rhubarbe</ingredient>. couper les <ingredient quantite=3>bananes</ingredient> en rondelles et les disposer sur la <ingredient quantite=1>compote</ingredient>. dans une jatte, émietter les <ingredient quantite=1>speculoos</ingredient> (pas trop finement, il faut qu’ il y ait quelques morceaux) ajouter le beurre ramolli et le <ingredient quantite=1>sucre roux</ingredient>. malaxer à la main de manière à <operation temps=6.86min espace=8>obtenir une <ingredient quantite=1>pâte</ingredient> à crumble</operation>. verser la pate sur la préparation et enfourner 20 min à <recipient>four</recipient> moyen. les <ingredient quantite=1>speculoos</ingredient> doivent être dorés. a manger tiède!
]]>
 </preparation>
</recette>
