<?xml version="1.0" encoding="utf-8"?>
<recette id="68531">
 <titre>La vraie bouillabaisse de Raoul</titre>
 <type>Plat principal</type>
 <niveau>Moyennement difficile</niveau>
 <cout>Assez Cher</cout>
 <ingredients>
 <p>Pour un fond de soupe (préparer deux fonds de soupe identiques avec ces ingrédients): </p>
 <p>1 kg de poissons de roche de Méditerranée (girelles, une tête de congre, rascasses, roucaous, gobis...) </p>
 <p>5 favouilles (petits crabes) </p>
 <p>2 tomates</p>
 <p>1 oignon</p>
 <p>2 gousses d’ ail</p>
 <p>2 branches de fenouil</p>
 <p>2 feuilles de laurier</p>
 <p>1, 5 l d’ eau</p>
 <p>huile</p>
 <p>Pour les poissons entiers (compter 300-400g de poissons par personne): </p>
 <p>2 rascasses</p>
 <p>4 queues de baudroie (lotte) </p>
 <p>1 Saint-Pierre</p>
 <p>2 rougets grondins</p>
 <p>2 roucaou</p>
 <p>2 vives</p>
 <p>huile d’ olive</p>
 <p>2 oignons</p>
 <p>2 tomates</p>
 <p>3 gousses d’ ail</p>
 <p>fenouil</p>
 <p>laurier</p>
 <p>safran</p>
 <p>600 g de pommes de terre</p>
 <p>Pour la rouille et les croûtons: </p>
 <p>piment de Cayenne en poudre</p>
 <p>safran</p>
 <p>croûtons de pain grillés frottés d’ ail</p>
 <p>croûtons de pain rassis</p>
 </ingredients>
 <preparation>
<![CDATA[
la veille préparer la <ingredient quantite=1>soupe</ingredient> de <ingredient quantite=1>roche</ingredient>: <operation temps=6.86min espace=35>faire revenir avec un peu d’</operation> huile les <ingredient quantite=1>oignons</ingredient> et l’ <ingredient quantite=2>ail</ingredient> dans une <recipient>cocotte</recipient> puis les <ingredient quantite=1>poissons entiers</ingredient> (pas besoin de les nettoyer ni de les vider). ajouter les <ingredient quantite=2>tomates</ingredient> coupées en morceaux, le <ingredient quantite=2>laurier</ingredient>, le <ingredient quantite=2>fenouil</ingredient>, saler et poivrer et <operation temps=6.86min espace=35>recouvrir d’ <ingredient quantite=1>eau</ingredient></operation>. <operation temps=6.86min espace=35>laisser cuire environ 1 heure à feu doux à moyen</operation>. mixer le tout. passer dans un presse purée puis dans une <recipient>passoire</recipient> plusieurs fois afin d’ enlever le maximum d’ arêtes. attention ne pas passer dans un <recipient>chinois</recipient> trop fin car il faut garder les sucs de la <ingredient quantite=1>soupe</ingredient> qui doit rester assez épaisse. la veille au soir: préparer la marinade. dans une autre <recipient>cocotte</recipient> disposer les <ingredient quantite=1>poissons</ingredient> nettoyés et écaillés. verser un filet d’ huile d’ <ingredient quantite=1>olive</ingredient>, <operation temps=0.25min espace=35>salez</operation> <operation temps=0.5min espace=35>poivrez</operation>. couper les <ingredient quantite=2>tomates</ingredient>, les <ingredient quantite=1>oignons</ingredient>, l’ <ingredient quantite=2>ail</ingredient> et les <ingredient quantite=1>pomme de terre</ingredient> en rondelles ou en dés. mettre tout ceci sur les <ingredient quantite=1>poissons</ingredient> et saupoudrer de <ingredient quantite=1>safran</ingredient>. ajouter le <ingredient quantite=2>laurier</ingredient> et le <ingredient quantite=2>fenouil</ingredient> et <operation temps=6.86min espace=35>laisser le tout</operation> mariner toute la nuit au frais (au moins 6 heures). le jour j: <operation temps=6.86min espace=35>faire cuire les <ingredient quantite=1>poissons</ingredient></operation>. faire bouillir un des deux <ingredient quantite=1>fond de soupe</ingredient> et mettre à cuire les <ingredient quantite=1>pommes de terre</ingredient>. faire bouillir l’ autre <ingredient quantite=1>fond de soupe</ingredient> et mettre à cuire les <ingredient quantite=1>poissons</ingredient> un à un en les enlevant dès qu’ ils sont cuits pour <operation temps=6.86min espace=35>faire cuire les suivants</operation>. l’ idéal serait d’ avoir un panier pour les tremper et les <operation temps=6.86min espace=35>ressortir sans les</operation> abimer. bien surveiller car le <ingredient quantite=1>poisson</ingredient> cuit assez vite. conserver en fin de cuisson les <ingredient quantite=1>poissons</ingredient> au chaud dans la <ingredient quantite=1>soupe</ingredient>. servir la <ingredient quantite=1>soupe</ingredient> avec les croutons et <ingredient quantite=1>la rouille</ingredient> (mayonnaise avec du <ingredient quantite=1>piment</ingredient> et du <ingredient quantite=1>safran</ingredient>) disposer les <ingredient quantite=1>poissons</ingredient> dans un <recipient>plat</recipient> avec les <ingredient quantite=1>pomme de terre</ingredient> et servir. pour les amateurs il est possible de mettre de la langouste ce qui n’ est pas obligatoire car pas dans la vraie recette. vin blanc
]]>
 </preparation>
</recette>
