<?xml version="1.0" encoding="utf-8"?>
<recette id="50081">
 <titre>Boulettes de viande farcies d’ Hilda</titre>
 <type>Plat principal</type>
 <niveau>Difficile</niveau>
 <cout>Bon marché</cout>
 <ingredients>
 <p>500 g de viande hachée à 5% de matière grasse</p>
 <p>500 g de viande hachée à 15% de matière grasse</p>
 <p>250 g de boulgour haché fin</p>
 <p>3 oignons</p>
 <p>sel poivre 4 épices</p>
 <p>huile de tournesol</p>
 </ingredients>
 <preparation>
<![CDATA[
c’ est exactement la même recette que " le kébé au <recipient>four</recipient> d’ hilda ", c’ est la présentation et le mode de cuisson qui changent. donc, vous <operation>préparez la pâte de <ingredient>viande</ingredient> et la farce</operation>... puis, vous <operation>prenez une petite boule de pâte de <ingredient>viande</ingredient> de la grosseur d’ une noix et vous la</operation> <operation>roulez entre les paumes de vos mains</operation>. <operation>posez la boule de pâte de <ingredient>viande</ingredient> dans le creux de votre main gauche, avec l’ index de la main droite, vous</operation> <operation>creusez un trou dans la boulette, vous</operation> allez avoir une sorte de puits. ensuite, en appuyant toujours avec l’ index sur les parois de ce puits, vous <operation>élargissez le trou (il</operation> faut que la cavité soit la plus grande possible et les parois du puits le plus <ingredient>fin</ingredient> possible, en <operation>faisant bien sûr attention de ne pas</operation> trouer la pâte). c’ est là que réside la difficulté de cette recette ; pour plus de facilité, trempez légèrement les mains dans de l’ eau froide. enfin, <operation>remplissez à l’</operation> aide d’ une cuillère à café avec un peu de farce, et <operation>refermez délicatement le trou en</operation> enserrant les bords du puits entre le pousse et les autres doigts de la main gauche et en tournant la boulette sur elle-même dans sa position verticale, en vous aidant de la main droite. <operation>rangez la boulette farcie sur une <recipient>planche</recipient></operation> et <operation>recouvrez d’ un film alimentaire, puis recommencez l’ opération avec une autre noix de pâte de <ingredient>viande</ingredient></operation>. une fois toutes les boulettes farcies, 2 présentations sont possibles: 1) repas principal chaud: <operation>faites cuire les boulettes dans un bouillon de volaille chaud, ça</operation> cuit assez vite. 2) buffet froid: <operation>faites chauffer un bain de friture</operation> et <operation>plongez rapidement les boulettes en plusieurs fois dans le bain de friture</operation>. attention ça cuit très vite! dès que les boulettes ont <operation>pris une jolie couleur marron clair</operation>, <operation>retirez - les avec une écumoire</operation> et <operation>rangez - les sur une assiette recouverte de papier</operation> absorbant. cette présentation es utilisée pour les buffets accompagnées de quartiers de citron. il faut avoir le coup de main pour creuser les boulettes mais le résultat en vaut la peine.
]]>
 </preparation>
</recette>
