<?xml version="1.0" encoding="utf-8"?>
<recette id="60641">
 <titre>Salade Azzuri</titre>
 <type>Plat principal</type>
 <niveau>Très facile</niveau>
 <cout>Moyen</cout>
 <ingredients>
 <p>1 oignon</p>
 <p>3 tomates </p>
 <p>2 filets de poulet </p>
 <p>4 tranches de jambon de Serrano</p>
 <p>200 g de salade croquante type Iceberg</p>
 <p>400 g de pommes de terre</p>
 <p>roquette</p>
 <p>huile d’ olive</p>
 <p>vinaigre balsamique</p>
 <p>sel, poivre</p>
 </ingredients>
 <preparation>
<![CDATA[
nettoyer les <ingredient>tomates</ingredient> et les couper en dés. mettre dans un <recipient>plat</recipient> et assaisonner d’ huile d’ <ingredient>olive</ingredient>, <ingredient>sel</ingredient>, <ingredient>poivre</ingredient> et <ingredient>vinaigre balsamique</ingredient>. <operation>laisser reposer</operation>. faire cuire les <ingredient>pommes de terre</ingredient> pelées et coupées en cubes à la vapeu ou à la <recipient>poêle</recipient>. cuire les <ingredient>filets de poulet</ingredient> et le <ingredient>jambon de serrano</ingredient> coupés en petits dés à la <recipient>poêle</recipient>. <operation>laisser dorer légèrement</operation>. dans un <recipient>plat</recipient>, verser les <ingredient>tomates</ingredient>, les <ingredient>pommes de terre</ingredient>, le <ingredient>poulet</ingredient>, le <ingredient>jambon de serrano</ingredient> et la salade <ingredient>croquante</ingredient>. ajouter l’ <ingredient>oignon</ingredient> coupé en morceaux. arosser de vinaigrette (3 cuillères à soupe d’ <ingredient>huile</ingredient>, 2 de <ingredient>vinaigre</ingredient>, <ingredient>sel</ingredient>, <ingredient>poivre</ingredient>). pour terminer, ajouter quelques feuilles de <ingredient>roquette</ingredient> et servir. un rosé sec
]]>
 </preparation>
</recette>
