<?xml version="1.0" encoding="utf-8"?>
<recette id="72081">
 <titre>Bananes flambées simples et très rapides</titre>
 <type>Dessert</type>
 <niveau>Facile</niveau>
 <cout>Bon marché</cout>
 <ingredients>
 <p>2 bananes bien mûres</p>
 <p>1 sachet de sucre vanillé</p>
 <p>1 petit verre de rhum (ou de Grand Marnier) </p>
 <p>2 noisettes de beurre</p>
 <p>1 briquet ou une allumette</p>
 </ingredients>
 <preparation>
<![CDATA[
<operation>faites chauffer une <recipient>poêle</recipient></operation>, <operation>faites - y</operation> fondre le <ingredient>beurre</ingredient> et <operation>ajoutez - y les <ingredient>bananes</ingredient></operation> coupées en long, <operation>faites dorer de chaque côté</operation>. saupoudrez de <ingredient>sucre vanillé</ingredient>, <operation>versez le</operation> <ingredient>rhum</ingredient> et <operation>faites flamber: lorsqu’ il n’ y</operation> aura plus de flammes, <operation>servez! vous</operation> pouvez aussi ajouter un filet de coulis de chocolat avant de <operation>servir</operation>.
]]>
 </preparation>
</recette>
