<?xml version="1.0" encoding="utf-8"?>
<recette id="70672">
 <titre>Légumes nouveaux sucrés-salés</titre>
 <type>Plat principal</type>
 <niveau>Facile</niveau>
 <cout>Moyen</cout>
 <ingredients>
 <p>1 botte de carottes nouvelles</p>
 <p>quelques pommes de terre nouvelles de Noirmoutiers</p>
 <p>1 botte de navets nouveaux</p>
 <p>quelques petits oignons nouveaux avec fanes</p>
 <p>persil haché</p>
 <p>3 cuillers à soupe de miel liquide</p>
 <p>1 à 2 fleurs d’ anis étoilé</p>
 <p>2 clous de girofle</p>
 <p>1 tablette de bouillon de volaille</p>
 <p>beurre frais</p>
 <p>sel, poivre</p>
 </ingredients>
 <preparation>
<![CDATA[
epluchez ou <operation>grattez les <ingredient>petits</ingredient> légumes</operation>. <operation>coupez les <ingredient>carottes</ingredient> en tronçons puis en bâtonnets</operation>, <operation>coupez les <ingredient>navets</ingredient> en 2 selon grosseur</operation>, laissez les <ingredient>pommes de terres</ingredient> entières ou <operation>coupez - les en 2 ou 4 selon grosseur, épluchez les <ingredient>oignons</ingredient> en</operation> laissant une partie de la tige. dans une <recipient>sauteuse</recipient>, <operation>faites faire fondre doucement le <ingredient>miel</ingredient></operation>. quand il est mousseux, <operation>ajoutez - y les légumes, remuez pour bien</operation> enrober le tout. parallèlement, préparez un <ingredient>bouillon de volaille</ingredient> avec 25 cl d’ eau chaude et la <ingredient>tablette</ingredient>. quand le mélange est prêt, <operation>versez jusqu’ à hauteur sur les <ingredient>petits</ingredient> légumes</operation>, <operation>salez légèrement</operation>, <operation>poivrez</operation>, ajoutez l’ <ingredient>anis étoilé</ingredient> et les clous de <ingredient>girofle</ingredient>. <operation>couvrez</operation> et <operation>faites cuire à feu moyen en</operation> surveillant le <ingredient>bouillon</ingredient> qui doit réduire pour ne <operation>faire qu’ un fond de jus</operation>. au bout de 20 min environ, vos <ingredient>petits</ingredient> légumes doivent cuits mais encore fermes. ajoutez alors du <ingredient>beurre frais</ingredient> en dés, du <ingredient>persil haché</ingredient>, <operation>remuez délicatement</operation> et <operation>servez en</operation> retirant la <ingredient>girofle</ingredient> et l’ <ingredient>anis étoilé</ingredient>. si vous aimez, vous pouvez également ajouter une endive coupée en long et par moitié, du fenouil émincé... cette recette peut s’ enrichir avec des <ingredient>petits</ingredient> pois <ingredient>frais</ingredient>, des fèves, des courgettes, j’ y ajoute alors du thym et une tomate coupée en deux. l’ <ingredient>anis étoilé</ingredient> et le <ingredient>miel</ingredient> donne une saveur subtile si l’ on aime le sucré - salé. cet accompagnement convient particulièrement avec une <ingredient>volaille</ingredient> ou viande blanche. le sucré de cette recette appréciera un magnifique rosé de provence <ingredient>frais</ingredient>, type bandol.
]]>
 </preparation>
</recette>
