<?xml version="1.0" encoding="utf-8"?>
<recette id="92883">
 <titre>Pain de thon à la catalane</titre>
 <type>Entrée</type>
 <niveau>Très facile</niveau>
 <cout>Bon marché</cout>
 <ingredients>
 <p>1 grosse boîte de thon à la catalane (environ 300 g) </p>
 <p>1 boîte de thon au naturel (environ 150 g) </p>
 <p>20 cl de crème semi-épaisse</p>
 <p>3 oeufs</p>
 <p>une petite bouteille (200 g ou 20 cl) de sauce tomate préparée sans viande (type sauce pour spaghetti aux légumes) </p>
 <p>un peu de sel et de poivre</p>
 </ingredients>
 <preparation>
<![CDATA[
hyper facile!! tout mélanger en veillant à bien écraser le <ingredient>thon</ingredient>. attention à ne pas trop saler. verser dans un <recipient>moule</recipient> à cake chemisé de papier de cuisson ou beurré. <operation>faire cuire thermostat 6/7 (200 ° c) pendant 40 min (pour un <recipient>four</recipient> à chaleur tournante) jusqu’ à ce que le cake se</operation> tienne bien. démouler et placer au frais pendant au moins 4 à 5 heures. servir bien froid avec une sauce <ingredient>crème</ingredient> / yaourt / ciboulette ou aneth, <ingredient>sel</ingredient> et poivre.
]]>
 </preparation>
</recette>
